IOTSocket/IOTSocketClient.py
IOTSocket/IOTSocketServer.py
IOTSocket/__init__.py
IOTSocket-0.3.3.dist-info/LICENSE
IOTSocket-0.3.3.dist-info/METADATA
IOTSocket-0.3.3.dist-info/WHEEL
IOTSocket-0.3.3.dist-info/top_level.txt
IOTSocket-0.3.3.dist-info/RECORD
