Metadata-Version: 2.1
Name: IOTSocket
Version: 0.3.3
Summary: to make bidirectional full-duplex comunications securely for iot devices
Home-page: https://github.com/AbhijithAJ/IOTSocket
Author: ABHIJITH BOPPE
Author-email: abhijithas.eh@gmail.com
License: MIT
Platform: UNKNOWN
Classifier: Development Status :: 5 - Production/Stable
Classifier: License :: OSI Approved :: MIT License
Classifier: Programming Language :: Python
Classifier: Programming Language :: Python :: 3.6
Classifier: Programming Language :: Python :: 3.8
Classifier: Topic :: Software Development :: Libraries :: Python Modules
Classifier: Intended Audience :: Developers
Classifier: Operating System :: Unix
Requires-Python: >=3.2
